Metadata-Version: 1.1
Name: bob.thesis.tiago
Version: 1.0.1
Summary: Tools to reproduce the experiments of the Ph.D. thesis from Tiago de Freitas Pereira
Home-page: https://gitlab.idiap.ch/bob/bob.thesis.tiago
Author: Tiago de Freitas Pereira
Author-email: tiago.pereira@idiap.ch
License: BSD
Keywords: bob,biometric recognition,evaluation
Platform: UNKNOWN
Classifier: Framework :: Bob
Classifier: Development Status :: 3 - Alpha
Classifier: Intended Audience :: Developers
Classifier: License :: OSI Approved :: BSD License
Classifier: Natural Language :: English
Classifier: Programming Language :: Python
Classifier: Topic :: Scientific/Engineering :: Artificial Intelligence
